formicidae_tracker_myrmidon.libs/libXfixes-e3b7d94c.so.3.1.0
formicidae_tracker_myrmidon.libs/libaom-fd0ed2c6.so.3.12.1
formicidae_tracker_myrmidon.libs/libavcodec-39f7de65.so.61.19.100
formicidae_tracker_myrmidon.libs/libavformat-8736f45c.so.61.7.100
formicidae_tracker_myrmidon.libs/libavutil-3b7f8b04.so.59.39.100
formicidae_tracker_myrmidon.libs/libbz2-a1e77c99.so.1.0.6
formicidae_tracker_myrmidon.libs/libcpptrace-223ee5ee.so.1.0.4
formicidae_tracker_myrmidon.libs/libdav1d-c2f19a9b.so.3.1.0
formicidae_tracker_myrmidon.libs/libdrm-b0291a67.so.2.4.0
formicidae_tracker_myrmidon.libs/libfort-hermes-cpp-6d5da020.so.0.5
formicidae_tracker_myrmidon.libs/libfort-myrmidon-9936f8f5.so.0.9
formicidae_tracker_myrmidon.libs/libfort-tags-9c8c3d2a.so.1.4
formicidae_tracker_myrmidon.libs/libfort-time-76e217d1.so.1.0.11
formicidae_tracker_myrmidon.libs/libfort-video-f2b7e42c.so
formicidae_tracker_myrmidon.libs/libmvec-2-06864e43.28.so
formicidae_tracker_myrmidon.libs/libnuma-3387f5e3.so.1.0.0
formicidae_tracker_myrmidon.libs/libprotobuf-0c7de7f4.so.31.0.1
formicidae_tracker_myrmidon.libs/libspng-fad51a82.so
formicidae_tracker_myrmidon.libs/libswresample-a7886e9b.so.5.3.100
formicidae_tracker_myrmidon.libs/libswscale-bf598ac9.so.8.3.100
formicidae_tracker_myrmidon.libs/libtbb-fa1bfe4f.so.12.5
formicidae_tracker_myrmidon.libs/libva-drm-b2ba5e7c.so.2.1300.0
formicidae_tracker_myrmidon.libs/libva-ed3913e3.so.2.1300.0
formicidae_tracker_myrmidon.libs/libva-x11-7ca6f2fd.so.2.1300.0
formicidae_tracker_myrmidon.libs/libvdpau-98dd745c.so.1.0.0
formicidae_tracker_myrmidon.libs/libx264-eee3854a.so.165
formicidae_tracker_myrmidon.libs/libx265-884f988d.so.209
formicidae_tracker_myrmidon.libs/libyaml-cpp-051a7531.so.0.7.0
fort_myrmidon/__init__.py
fort_myrmidon/_fort_myrmidon.cpython-39-x86_64-linux-gnu.so
fort_myrmidon/_fort_myrmidon.pyi
formicidae_tracker_myrmidon-0.9.0.dist-info/METADATA
formicidae_tracker_myrmidon-0.9.0.dist-info/WHEEL
formicidae_tracker_myrmidon-0.9.0.dist-info/RECORD
