Metadata-Version: 2.2
Name: formicidae-tracker-myrmidon
Version: 0.9.0
Summary: Python bindings for fort-myrmidon, a tracking data post-processing library
Author-Email: Alexandre Tuleu <alexandre.tuleu.2005@polytechnique.org>
License: GNU Lesser General Public License v3 (LGPLv3)
Classifier: License :: OSI Approved :: GNU Lesser General Public License v3 (LGPLv3)
Classifier: Programming Language :: Python :: 3
Classifier: Programming Language :: Python :: 3 :: Only
Classifier: Programming Language :: Python :: 3.7
Classifier: Programming Language :: Python :: 3.8
Classifier: Programming Language :: Python :: 3.9
Classifier: Programming Language :: Python :: 3.10
Classifier: Programming Language :: Python :: 3.11
Classifier: Programming Language :: Python :: Implementation :: CPython
Project-URL: Homepage, https://github.com/formicidae-tracker/myrmidon
Project-URL: Repository, https://github.com/formicidae-tracker/myrmidon
Project-URL: Issues, https://github.com/formicidae-tracker/myrmidon/issues
Requires-Python: >=3.7
Requires-Dist: pandas
Requires-Dist: tqdm
